groundingdino/__init__.py
groundingdino/version.py
groundingdino/datasets/__init__.py
groundingdino/datasets/transforms.py
groundingdino/models/__init__.py
groundingdino/models/registry.py
groundingdino/models/GroundingDINO/__init__.py
groundingdino/models/GroundingDINO/bertwarper.py
groundingdino/models/GroundingDINO/fuse_modules.py
groundingdino/models/GroundingDINO/groundingdino.py
groundingdino/models/GroundingDINO/ms_deform_attn.py
groundingdino/models/GroundingDINO/transformer.py
groundingdino/models/GroundingDINO/transformer_vanilla.py
groundingdino/models/GroundingDINO/utils.py
groundingdino/models/GroundingDINO/backbone/__init__.py
groundingdino/models/GroundingDINO/backbone/backbone.py
groundingdino/models/GroundingDINO/backbone/position_encoding.py
groundingdino/models/GroundingDINO/backbone/swin_transformer.py
groundingdino/util/__init__.py
groundingdino/util/box_ops.py
groundingdino/util/get_tokenlizer.py
groundingdino/util/inference.py
groundingdino/util/misc.py
groundingdino/util/slconfig.py
groundingdino/util/slio.py
gddet-0.1.4.dist-info/LICENSE
gddet-0.1.4.dist-info/METADATA
gddet-0.1.4.dist-info/WHEEL
gddet-0.1.4.dist-info/top_level.txt
gddet-0.1.4.dist-info/RECORD
