Metadata-Version: 2.1
Name: gddet
Version: 0.1.4
Summary: open-set object detector
Home-page: https://github.com/IDEA-Research/GroundingDINO
Author: H-AI
License: Apache License V2.0
Platform: UNKNOWN
License-File: LICENSE
